bluegenes/__init__.py
bluegenes/errors.py
bluegenes/genes.py
bluegenes/optimization.py
bluegenes-0.0.3.dist-info/METADATA
bluegenes-0.0.3.dist-info/WHEEL
bluegenes-0.0.3.dist-info/licenses/license
bluegenes-0.0.3.dist-info/RECORD
