Metadata-Version: 2.1
Name: bluegenes
Version: 0.0.3
Summary: Working-man's library for genetic algorithms
Project-URL: Homepage, https://github.com/k98kurz/bluegenes-python
Project-URL: Bug Tracker, https://github.com/k98kurz/bluegenes-python/issues
Author-email: k98kurz <k98kurz@gmail.com>
License-File: license
Classifier: Development Status :: 3 - Alpha
Classifier: Intended Audience :: Science/Research
Classifier: License :: OSI Approved :: ISC License (ISCL)
Classifier: Operating System :: OS Independent
Classifier: Programming Language :: Python :: 3
Classifier: Topic :: Scientific/Engineering :: Artificial Intelligence
Classifier: Topic :: Scientific/Engineering :: Artificial Life
Requires-Python: >=3.9
